fabdb/__init__.py
fabdb/__main__.py
fabdb/client.py
fabdb-0.0.1.dist-info/METADATA
fabdb-0.0.1.dist-info/WHEEL
fabdb-0.0.1.dist-info/licenses/LICENSE
fabdb-0.0.1.dist-info/RECORD
