Metadata-Version: 2.1
Name: fabdb
Version: 0.0.1
Summary: CLI and Utility for fabdb.net
Project-URL: Homepage, https://github.com/dorthu/fabdb-python
Project-URL: Bug Tracker, https://github.com/dorthu/fabdb-python/issues
Author-email: dorthu <dorthu2+fabdb-python@gmail.com>
License: Redistribution and use in source and binary forms, with or without
License-File: LICENSE
Classifier: License :: OSI Approved :: BSD License
Classifier: Operating System :: OS Independent
Classifier: Programming Language :: Python :: 3
Requires-Python: >=3.7
